cli.py
cli_init.py
examples/__init__.py
konduit/__init__.py
konduit/base_inference.py
konduit/client.py
konduit/inference.py
konduit/json_utils.py
konduit/load.py
konduit/server.py
konduit/utils.py
tests/__init__.py
tests/simple.py
tests/test_bert_serving.py
tests/test_client.py
tests/test_client_serde.py
tests/test_docs.py
tests/test_json.py
tests/test_json_utils.py
tests/test_load_yaml.py
tests/test_pid_storage.py
tests/test_python_serving.py
tests/test_python_serving_file.py
tests/test_setup_and_run.py
tests/test_tf_yaml_inference.py
tests/test_transform_process.py
tests/test_utils.py
tests/test_wordpiece_tokenizer.py
tests/utils.py
konduit-0.1.11.dist-info/METADATA
konduit-0.1.11.dist-info/WHEEL
konduit-0.1.11.dist-info/entry_points.txt
konduit-0.1.11.dist-info/top_level.txt
konduit-0.1.11.dist-info/RECORD
