Metadata-Version: 2.1
Name: konduit
Version: 0.1.11
Summary: konduit: Enterprise Runtime for Machine Learning Models
Home-page: https://github.com/KonduitAI/konduit-serving
Author: Max Pumperla, Shams Ul Azeem
Author-email: max@konduit.ai, shams@konduit.ai
License: Apache
Platform: UNKNOWN
Classifier: Development Status :: 3 - Alpha
Classifier: Intended Audience :: Developers
Classifier: Environment :: Console
Classifier: License :: OSI Approved :: Apache Software License
Classifier: Operating System :: OS Independent
Classifier: Programming Language :: Python
Classifier: Programming Language :: Python :: 3
Requires-Dist: requests (>=2.22.0)
Requires-Dist: numpy (<=1.16.4)
Requires-Dist: pyarrow (==0.13.0)
Requires-Dist: requests-toolbelt (>=0.9.1)
Requires-Dist: pandas (<=0.24.2)
Requires-Dist: Cython
Requires-Dist: pydl4j
Requires-Dist: pydatavec
Requires-Dist: pyyaml
Requires-Dist: click
Requires-Dist: packaging
Requires-Dist: hurry.filesize
Provides-Extra: codegen
Requires-Dist: jsonschema2popo ; extra == 'codegen'
Provides-Extra: dev
Requires-Dist: black ; extra == 'dev'
Requires-Dist: pre-commit ; extra == 'dev'
Provides-Extra: tests
Requires-Dist: pytest ; extra == 'tests'
Requires-Dist: pytest-pep8 ; extra == 'tests'
Requires-Dist: pytest-cov ; extra == 'tests'
Requires-Dist: mock ; extra == 'tests'
